Workbook

Sheet Sheet1
A1: Date | B1: Time | C1: User | D1: =VLOOKUP(C1, Sheet2!A1:B21, 2, FALSE) -> #N/A | E1: Context
A2: 4/21/22 | B2: 22:04 | C2: Ivy wen LPC | D2: =VLOOKUP(C2, Sheet2!$A$1:$B$21, 2, FALSE) -> 0 | E2: And it should be ok with the UTA server?
A3: 4/24/22 | B3: 21:28 | C3: Johnny EMSD LPC | D3: =VLOOKUP(C3, Sheet2!$A$1:$B$21, 2, FALSE) -> 1 | E3: @85291405205 Can you help to take videos for demo if the BIM Model Viewer function is ready?
A4: 4/24/22 | B4: 21:32 | C4: Ivy wen LPC | D4: =VLOOKUP(C4, Sheet2!$A$1:$B$21, 2, FALSE) -> 0 | E4: Which function?
A5: 4/24/22 | B5: 21:35 | C5: Johnny EMSD LPC | D5: =VLOOKUP(C5, Sheet2!$A$1:$B$21, 2, FALSE) -> 1 | E5: Compare model, link model
A6: 4/24/22 | B6: 21:35 | C6: Ivy wen LPC | D6: =VLOOKUP(C6, Sheet2!$A$1:$B$21, 2, FALSE) -> 0 | E6: Not ready ya
A7: 4/24/22 | B7: 21:35 | C7: Ivy wen LPC | D7: =VLOOKUP(C7, Sheet2!$A$1:$B$21, 2, FALSE) -> 0 | E7: 😅
A8: 4/24/22 | B8: 21:35 | C8: Johnny EMSD LPC | D8: =VLOOKUP(C8, Sheet2!$A$1:$B$21, 2, FALSE) -> 1 | E8: I know
A9: 4/24/22 | B9: 21:36 | C9: Johnny EMSD LPC | D9: =VLOOKUP(C9, Sheet2!$A$1:$B$21, 2, FALSE) -> 1 | E9: I also want to know the navigation function, is that any update or just the previous version?
A10: 4/24/22 | B10: 21:36 | C10: Ivy wen LPC | D10: =VLOOKUP(C10, Sheet2!$A$1:$B$21, 2, FALSE) -> 0 | E10: Navigation?
A11: 4/24/22 | B11: 21:40 | C11: Johnny EMSD LPC | D11: =VLOOKUP(C11, Sheet2!$A$1:$B$21, 2, FALSE) -> 1 | E11: The function allow user to walk around inside the model
A12: 4/24/22 | B12: 21:41 | C12: Ivy wen LPC | D12: =VLOOKUP(C12, Sheet2!$A$1:$B$21, 2, FALSE) -> 0 | E12: <Media omitted>
A13: 4/24/22 | B13: 22:05 | C13: Johnny EMSD LPC | D13: =VLOOKUP(C13, Sheet2!$A$1:$B$21, 2, FALSE) -> 1 | E13: <Media omitted>
... A2271: 6/12/24 | B2271: 22:58 | C2271: Eric Wong LPC | D2271: =VLOOKUP(C2271, Sheet2!$A$1:$B$21, 2, FALSE) -> 20 | E2271: A warm reminder that we have sent out updated design doc via email on 7th June. Feel free to contact us for any enquiry. Your response by 14th June 2024 is greatly appreciated to proceed the captioned project, prioritising on addressing technical comments, if any.

Sheet Sheet2
A1: Ivy wen LPC | B1: 0
A2: Johnny EMSD LPC | B2: 1
A3: Seria LPC | B3: 2
A4: tim LPC | B4: 3
A5: +852 5174 0106 | B5: 4
A6: kmj | B6: 5
A7: Dr. Tang LPC | B7: 6
A8: Ivy wen LPC2 | B8: 7
A9: Didi LPC | B9: 8
A10: Vivian EMSD LPC | B10: 9
A11: +852 9461 9188 | B11: 10
A12: David Cho LPC | B12: 11
... A21: Eric Wong LPC | B21: 20
